README.rst
setup.py
Pelops.egg-info/PKG-INFO
Pelops.egg-info/SOURCES.txt
Pelops.egg-info/dependency_links.txt
Pelops.egg-info/requires.txt
Pelops.egg-info/top_level.txt
pelops/__init__.py
pelops/abstractmicroservice.py
pelops/historyagent.py
pelops/imagemqttnessageconverter.py
pelops/myconfigtools.py
pelops/mythreading.py
pelops/logging/__init__.py
pelops/logging/mqtthandler.py
pelops/logging/mylogger.py
pelops/monitoring_agent/__init__.py
pelops/monitoring_agent/monitoringagent.py
pelops/monitoring_agent/states/__init__.py
pelops/monitoring_agent/states/aagentstate.py
pelops/monitoring_agent/states/active.py
pelops/monitoring_agent/states/event_ids.py
pelops/monitoring_agent/states/history_type.py
pelops/monitoring_agent/states/initialized.py
pelops/monitoring_agent/states/machinelogger.py
pelops/monitoring_agent/states/onboarded.py
pelops/monitoring_agent/states/onboarding.py
pelops/monitoring_agent/states/state_ids.py
pelops/monitoring_agent/states/state_machine.py
pelops/monitoring_agent/states/terminiating.py
pelops/monitoring_agent/states/uninitialized.py
pelops/pubsub/__init__.py
pelops/pubsub/apubsub.py
pelops/pubsub/mymqttclient.py
pelops/pubsub/pubsub_factory.py
pelops/pubsub/pythonqueue.py
pelops/pubsub/statistics.py
pelops/schema/__init__.py
pelops/schema/abstractmicroservice.py
pelops/schema/apubsub.py
pelops/schema/monitoring_agent.py
pelops/schema/mylogger.py
pelops/ui/__init__.py
pelops/ui/tools.py
pelops/ui/ui.py
tests_unit/__init__.py
tests_unit/exampleservice.py
tests_unit/test_historyagent_aggregated_import.py
tests_unit/test_historyagent_basic.py
tests_unit/test_historyagent_direct_import.py
tests_unit/test_microservice_mqtt.py
tests_unit/test_microservice_queue.py
tests_unit/test_myconfigtools.py
tests_unit/test_mylogger.py
tests_unit/test_mymqttclient.py
tests_unit/test_pythonqueue.py